serving_template
